crt/__init__.py
crt/_version.py
crt/cli.py
crt-0.0.4.dist-info/METADATA
crt-0.0.4.dist-info/RECORD
crt-0.0.4.dist-info/WHEEL
crt-0.0.4.dist-info/entry_points.txt
crt-0.0.4.dist-info/top_level.txt
