Metadata-Version: 2.1
Name: crt
Version: 0.0.4
Summary: UNKNOWN
Home-page: https://github.com/rojopolis/crt/wiki
Author: Robert Jordan
Author-email: rojopolis@deba.cl
License: UNKNOWN
Platform: UNKNOWN
Requires-Dist: click (==6.7)
